upx_elf_parser/__init__.py
upx_elf_parser/cli.py
upx_elf_parser/exceptions.py
upx_elf_parser/models.py
upx_elf_parser/parser.py
upx_elf_parser/py.typed
upx_elf_parser-0.1.0.dist-info/METADATA
upx_elf_parser-0.1.0.dist-info/WHEEL
upx_elf_parser-0.1.0.dist-info/entry_points.txt
upx_elf_parser-0.1.0.dist-info/licenses/LICENSE
upx_elf_parser-0.1.0.dist-info/RECORD
