Metadata-Version: 2.4
Name: upx-elf-parser
Version: 0.1.0
Summary: A Python library for parsing UPX-packed ELF files
Project-URL: Homepage, https://github.com/bolin8017/upx-elf-parser
Project-URL: Documentation, https://github.com/bolin8017/upx-elf-parser#readme
Project-URL: Repository, https://github.com/bolin8017/upx-elf-parser
Project-URL: Issues, https://github.com/bolin8017/upx-elf-parser/issues
Author: bolin8017
License-Expression: MIT
License-File: LICENSE
Keywords: binary,elf,malware-analysis,parser,reverse-engineering,security,upx
Classifier: Development Status :: 4 - Beta
Classifier: Intended Audience :: Developers
Classifier: Intended Audience :: Information Technology
Classifier: Intended Audience :: Science/Research
Classifier: License :: OSI Approved :: MIT License
Classifier: Operating System :: POSIX :: Linux
Classifier: Programming Language :: Python :: 3
Classifier: Programming Language :: Python :: 3.10
Classifier: Programming Language :: Python :: 3.11
Classifier: Programming Language :: Python :: 3.12
Classifier: Programming Language :: Python :: 3.13
Classifier: Topic :: Security
Classifier: Topic :: Software Development :: Disassemblers
Classifier: Topic :: System :: Software Distribution
Classifier: Typing :: Typed
Requires-Python: >=3.10
Requires-Dist: pyelftools>=0.29
Provides-Extra: dev
Requires-Dist: mypy>=1.10; extra == 'dev'
Requires-Dist: pytest-cov>=4.0; extra == 'dev'
Requires-Dist: pytest>=8.0; extra == 'dev'
Requires-Dist: ruff>=0.4; extra == 'dev'
